ims_api_connector/__init__.py
ims_api_connector/connector.py
ims_api_connector/connector_test.py
ims_api_connector-2018.2.data/data/README.md
ims_api_connector-2018.2.dist-info/METADATA
ims_api_connector-2018.2.dist-info/RECORD
ims_api_connector-2018.2.dist-info/WHEEL
ims_api_connector-2018.2.dist-info/top_level.txt
