Metadata-Version: 2.1
Name: ims-api-connector
Version: 2018.2
Summary: A connector for the FTP Technologies IMS API
Home-page: https://github.com/initialed85/ims-python-api-connector
Author: Edward Beech
Author-email: edward.beech@ftpsolutions.com.au
License: MIT
Keywords: sample setuptools development
Platform: UNKNOWN
Classifier: Development Status :: 3 - Alpha
Classifier: Intended Audience :: Developers
Classifier: Topic :: Software Development :: Libraries
Classifier: License :: OSI Approved :: MIT License
Classifier: Programming Language :: Python :: 2.7
Classifier: Programming Language :: Python :: 3.6
Provides-Extra: test
Provides-Extra: dev
